ninja_rest/__init__.py
ninja_rest/authentication.py
ninja_rest/generics.py
ninja_rest/mixins.py
ninja_rest/pagination.py
ninja_rest/permissions.py
ninja_rest/schemas.py
ninja_rest/viewsets.py
ninja_rest-0.1.0.dist-info/METADATA
ninja_rest-0.1.0.dist-info/WHEEL
ninja_rest-0.1.0.dist-info/top_level.txt
ninja_rest-0.1.0.dist-info/RECORD
