Metadata-Version: 2.4
Name: ninja_rest
Version: 0.1.0
Summary: A Django REST Framework-like package using Django Ninja
Home-page: https://github.com/pradip-v2/ninja_rest
Author: Pradip Bankar
Author-email: pradipbankar0097@gmail.com
Project-URL: Documentation, https://github.com/pradip-v2/ninja_rest
Project-URL: Bug Reports, https://github.com/pradip-v2/ninja_rest/issues
Project-URL: Source Code, https://github.com/pradip-v2/ninja_rest
Keywords: django,rest,api,django-ninja,viewsets
Classifier: Development Status :: 3 - Alpha
Classifier: Framework :: Django
Classifier: Intended Audience :: Developers
Classifier: License :: OSI Approved :: MIT License
Classifier: Programming Language :: Python :: 3
Classifier: Programming Language :: Python :: 3.8
Classifier: Programming Language :: Python :: 3.9
Classifier: Programming Language :: Python :: 3.10
Classifier: Programming Language :: Python :: 3.11
Classifier: Topic :: Software Development :: Libraries :: Python Modules
Requires-Python: >=3.8
Requires-Dist: django>=3.2
Requires-Dist: django-ninja>=0.22.0
Requires-Dist: pydantic>=2.0.0
Dynamic: author
Dynamic: author-email
Dynamic: classifier
Dynamic: description
Dynamic: description-content-type
Dynamic: home-page
Dynamic: keywords
Dynamic: project-url
Dynamic: requires-dist
Dynamic: requires-python
Dynamic: summary
